CortexAi/__init__.py
CortexAi/config/README.md
CortexAi/config/__init__.py
CortexAi/config/config.py
CortexAi/config/sample_config.yml
CortexAi/config/schema.py
cortexai-0.1.0.dist-info/licenses/LICENSE
cortexai-0.1.0.dist-info/METADATA
cortexai-0.1.0.dist-info/WHEEL
cortexai-0.1.0.dist-info/top_level.txt
cortexai-0.1.0.dist-info/RECORD
